[
  {
    "object_id": 1,
    "area": 220268,
    "bbox": [
      200,
      1503,
      877,
      301
    ],
    "predicted_iou": 1.023789882659912,
    "stability_score": 0.9922824501991272
  },
  {
    "object_id": 2,
    "area": 46136,
    "bbox": [
      599,
      1717,
      401,
      202
    ],
    "predicted_iou": 1.0029242038726807,
    "stability_score": 0.9913488030433655
  },
  {
    "object_id": 3,
    "area": 32519,
    "bbox": [
      395,
      1783,
      303,
      136
    ],
    "predicted_iou": 0.9980378150939941,
    "stability_score": 0.9900608658790588
  },
  {
    "object_id": 4,
    "area": 24251,
    "bbox": [
      143,
      1810,
      262,
      109
    ],
    "predicted_iou": 0.9903988242149353,
    "stability_score": 0.9806459546089172
  },
  {
    "object_id": 5,
    "area": 9381,
    "bbox": [
      782,
      1850,
      217,
      69
    ],
    "predicted_iou": 0.9866270422935486,
    "stability_score": 0.9861360788345337
  },
  {
    "object_id": 6,
    "area": 4850,
    "bbox": [
      974,
      1858,
      105,
      61
    ],
    "predicted_iou": 0.9841658473014832,
    "stability_score": 0.9875102639198303
  },
  {
    "object_id": 7,
    "area": 1736,
    "bbox": [
      304,
      1762,
      39,
      47
    ],
    "predicted_iou": 0.9690699577331543,
    "stability_score": 0.9856897592544556
  },
  {
    "object_id": 8,
    "area": 5747,
    "bbox": [
      343,
      1765,
      221,
      44
    ],
    "predicted_iou": 0.9625162482261658,
    "stability_score": 0.9644201397895813
  },
  {
    "object_id": 9,
    "area": 2942,
    "bbox": [
      984,
      1802,
      95,
      42
    ],
    "predicted_iou": 0.9533658027648926,
    "stability_score": 0.9729187488555908
  },
  {
    "object_id": 10,
    "area": 6123,
    "bbox": [
      902,
      1799,
      177,
      46
    ],
    "predicted_iou": 0.9504917860031128,
    "stability_score": 0.9770634770393372
  },
  {
    "object_id": 11,
    "area": 3083,
    "bbox": [
      902,
      1800,
      113,
      39
    ],
    "predicted_iou": 0.9455558657646179,
    "stability_score": 0.9572514295578003
  },
  {
    "object_id": 12,
    "area": 28762,
    "bbox": [
      136,
      1810,
      940,
      109
    ],
    "predicted_iou": 0.942602276802063,
    "stability_score": 0.9660744667053223
  },
  {
    "object_id": 13,
    "area": 6623,
    "bbox": [
      854,
      1756,
      225,
      49
    ],
    "predicted_iou": 0.9378241300582886,
    "stability_score": 0.9680345058441162
  },
  {
    "object_id": 14,
    "area": 2156,
    "bbox": [
      321,
      1635,
      58,
      38
    ],
    "predicted_iou": 0.9352575540542603,
    "stability_score": 0.9734310507774353
  },
  {
    "object_id": 15,
    "area": 4272,
    "bbox": [
      380,
      1639,
      137,
      36
    ],
    "predicted_iou": 0.9259533286094666,
    "stability_score": 0.9658671617507935
  },
  {
    "object_id": 16,
    "area": 6790,
    "bbox": [
      207,
      1566,
      116,
      65
    ],
    "predicted_iou": 0.9146832227706909,
    "stability_score": 0.9699782729148865
  },
  {
    "object_id": 17,
    "area": 1435092,
    "bbox": [
      5,
      222,
      1071,
      1697
    ],
    "predicted_iou": 1.0462353229522705,
    "stability_score": 0.9911543130874634
  },
  {
    "object_id": 18,
    "area": 263677,
    "bbox": [
      0,
      0,
      1077,
      270
    ],
    "predicted_iou": 1.020816683769226,
    "stability_score": 0.9911530017852783
  },
  {
    "object_id": 19,
    "area": 250952,
    "bbox": [
      137,
      1503,
      941,
      416
    ],
    "predicted_iou": 0.9962997436523438,
    "stability_score": 0.9750102162361145
  }
]